lycosa/__init__.py
lycosa/sender/__init__.py
lycosa/sender/attachment_handler.py
lycosa/sender/email_builder.py
lycosa/sender/email_client.py
lycosa/sender/email_sender.py
lycosa/sender/email_service.py
lycosa/sender/file_validator.py
lycosa-1.0.0.dist-info/licenses/LICENSE
lycosa-1.0.0.dist-info/METADATA
lycosa-1.0.0.dist-info/WHEEL
lycosa-1.0.0.dist-info/top_level.txt
lycosa-1.0.0.dist-info/RECORD
