Metadata-Version: 2.4
Name: lycosa
Version: 1.0.0
Summary: lycosa is a python library that allows you to easily manage emails
Home-page: https://github.com/Tina-1300/lycosa
Author: Tina
Author-email: tina.xytrfgthuji1348@gmail.com
License: MIT
Classifier: Programming Language :: Python :: 3
Classifier: License :: OSI Approved :: MIT License
Classifier: Operating System :: OS Independent
Classifier: Intended Audience :: Developers
Classifier: Topic :: Communications :: Email
Requires-Python: >=3.13.0
License-File: LICENSE
Dynamic: license-file
